brewblox_dev/__init__.py
brewblox_dev/__main__.py
brewblox_dev/repository.py
brewblox_dev/utils.py
brewblox_dev-2.3.0.dist-info/LICENSE
brewblox_dev-2.3.0.dist-info/METADATA
brewblox_dev-2.3.0.dist-info/WHEEL
brewblox_dev-2.3.0.dist-info/entry_points.txt
brewblox_dev-2.3.0.dist-info/RECORD
